kivy_garden/modernmenu/__init__.py
kivy_garden/modernmenu/_version.py
kivy_garden.modernmenu-0.1.0.dev0.dist-info/AUTHORS.txt
kivy_garden.modernmenu-0.1.0.dev0.dist-info/LICENSE
kivy_garden.modernmenu-0.1.0.dev0.dist-info/LICENSE.txt
kivy_garden.modernmenu-0.1.0.dev0.dist-info/METADATA
kivy_garden.modernmenu-0.1.0.dev0.dist-info/WHEEL
kivy_garden.modernmenu-0.1.0.dev0.dist-info/top_level.txt
kivy_garden.modernmenu-0.1.0.dev0.dist-info/RECORD
