Metadata-Version: 2.1
Name: kivy_garden.modernmenu
Version: 0.1.0.dev0
Summary: A modern contextmenu for Kivy
Home-page: https://github.com/kivy-garden/modernmenu
Author: Kivy
Author-email: kivy@kivy.org
License: UNKNOWN
Project-URL: Bug Reports, https://github.com/kivy-garden/modernmenu/issues
Project-URL: Source, https://github.com/kivy-garden/modernmenu
Keywords: Kivy kivy-garden
Platform: UNKNOWN
Classifier: Development Status :: 4 - Beta
Classifier: Intended Audience :: Developers
Classifier: Topic :: Software Development :: Libraries
Classifier: License :: OSI Approved :: MIT License
Classifier: Programming Language :: Python :: 3.5
Classifier: Programming Language :: Python :: 3.6
Classifier: Programming Language :: Python :: 3.7
Classifier: Programming Language :: Python :: 3.8
Provides-Extra: dev
Provides-Extra: travis
